CHANGES.txt
CREDITS.txt
LICENSE.txt
MANIFEST.in
README.rst
bootstrap.py
buildout.cfg
setup.py
tox.ini
more/__init__.py
more.static.egg-info/PKG-INFO
more.static.egg-info/SOURCES.txt
more.static.egg-info/dependency_links.txt
more.static.egg-info/namespace_packages.txt
more.static.egg-info/not-zip-safe
more.static.egg-info/requires.txt
more.static.egg-info/top_level.txt
more/static/__init__.py
more/static/core.py
more/static/tests/__init__.py
more/static/tests/test_static.py