Metadata-Version: 1.1
Name: more.static
Version: 0.10
Summary: BowerStatic integration for Morepath
Home-page: https://github.com/morepath/more.static
Author: Martijn Faassen
Author-email: faassen@startifact.com
License: BSD
Keywords: morepath bowerstatic bower
Platform: UNKNOWN
Classifier: License :: OSI Approved :: BSD License
Classifier: Programming Language :: Python :: 2
Classifier: Programming Language :: Python :: 2.7
Classifier: Programming Language :: Python :: 3
Classifier: Programming Language :: Python :: 3.3
Classifier: Programming Language :: Python :: 3.4
Classifier: Programming Language :: Python :: 3.5
